read_fits.py
package/MLS.py
package/__init__.py
package/extremum.py
package/ikernal23.py
package/make_3dpicture.py
package/making_plot_contour.py
CTGUAstronomy_testlib-1.0.2.dist-info/METADATA
CTGUAstronomy_testlib-1.0.2.dist-info/WHEEL
CTGUAstronomy_testlib-1.0.2.dist-info/top_level.txt
CTGUAstronomy_testlib-1.0.2.dist-info/RECORD
