Metadata-Version: 2.1
Name: CTGUAstronomy-testlib
Version: 1.0.2
Summary: A normal test file
Home-page: UNKNOWN
Author: ctguer_liuchvn
Author-email: liuchvn@qq.com
License: UNKNOWN
Platform: UNKNOWN
